codex_sdk/__init__.py
codex_sdk/abort.py
codex_sdk/app_server.py
codex_sdk/codex.py
codex_sdk/config_overrides.py
codex_sdk/events.py
codex_sdk/exceptions.py
codex_sdk/exec.py
codex_sdk/hooks.py
codex_sdk/integrations/__init__.py
codex_sdk/integrations/pydantic_ai.py
codex_sdk/integrations/pydantic_ai_model.py
codex_sdk/items.py
codex_sdk/options.py
codex_sdk/telemetry.py
codex_sdk/thread.py
codex_sdk_python-0.81.0.dist-info/WHEEL
codex_sdk_python-0.81.0.dist-info/METADATA
codex_sdk_python-0.81.0.dist-info/RECORD
