Metadata-Version: 2.3
Name: codex-sdk-python
Version: 0.81.0
Summary: Python SDK for the Codex CLI agent with async threads, streaming events, and structured outputs
Keywords: codex,sdk,python,api,cli,agent,async,streaming
Author: Vectorfy Co
Author-email: Vectorfy Co <git@vectorfy.co>
License: Apache-2.0
Classifier: Development Status :: 4 - Beta
Classifier: Intended Audience :: Developers
Classifier: License :: OSI Approved :: Apache Software License
Classifier: Operating System :: OS Independent
Classifier: Programming Language :: Python :: 3
Classifier: Programming Language :: Python :: 3.8
Classifier: Programming Language :: Python :: 3.9
Classifier: Programming Language :: Python :: 3.10
Classifier: Programming Language :: Python :: 3.11
Classifier: Programming Language :: Python :: 3.12
Classifier: Topic :: Software Development :: Libraries :: Python Modules
Classifier: Topic :: Software Development :: Build Tools
Requires-Dist: logfire ; extra == 'logfire'
Requires-Dist: pydantic>=2 ; extra == 'pydantic'
Requires-Dist: pydantic-ai ; python_full_version >= '3.10' and extra == 'pydantic-ai'
Maintainer: Vectorfy Co
Maintainer-email: Vectorfy Co <git@vectorfy.co>
Requires-Python: >=3.8
Project-URL: Changelog, https://github.com/vectorfy-co/codex-sdk-python/blob/main/CHANGELOG_SDK.md
Project-URL: Documentation, https://github.com/vectorfy-co/codex-sdk-python#readme
Project-URL: Homepage, https://vectorfy.co
Project-URL: Issues, https://github.com/vectorfy-co/codex-sdk-python/issues
Project-URL: Repository, https://github.com/vectorfy-co/codex-sdk-python
Provides-Extra: logfire
Provides-Extra: pydantic
Provides-Extra: pydantic-ai
